src/exe_unit_w47_rtl.sv
/* Generated by Yosys 0.34 (git sha1 4a1b5599258, gcc 13.2.1 -march=x86-64 -mtune=generic -O2 -fno-plt -fexceptions -fstack-clash-protection -fcf-protection -ffile-prefix-map=/build/yosys/src=/usr/src/debug/yosys -fPIC -Os) */

module exe_unit_w47_rtl(i_argA, i_argB, i_oper, i_clk, i_rsn, o_result, o_status);
  wire _000_;
  wire _001_;
  wire _002_;
  wire _003_;
  wire _004_;
  wire _005_;
  wire _006_;
  wire _007_;
  wire _008_;
  wire _009_;
  wire _010_;
  wire _011_;
  wire _012_;
  wire _013_;
  wire _014_;
  wire _015_;
  wire _016_;
  wire _017_;
  wire _018_;
  wire _019_;
  wire _020_;
  wire _021_;
  wire _022_;
  wire _023_;
  wire _024_;
  wire _025_;
  wire _026_;
  wire _027_;
  wire _028_;
  wire _029_;
  wire _030_;
  wire _031_;
  wire _032_;
  wire _033_;
  wire _034_;
  wire _035_;
  wire _036_;
  wire _037_;
  wire _038_;
  wire _039_;
  wire _040_;
  wire _041_;
  wire _042_;
  wire _043_;
  wire _044_;
  wire _045_;
  wire _046_;
  wire _047_;
  wire _048_;
  wire _049_;
  wire _050_;
  wire _051_;
  wire _052_;
  wire _053_;
  wire _054_;
  wire _055_;
  wire _056_;
  wire _057_;
  wire _058_;
  wire _059_;
  wire _060_;
  wire _061_;
  wire _062_;
  wire _063_;
  wire _064_;
  wire _065_;
  wire _066_;
  wire _067_;
  wire _068_;
  wire _069_;
  wire _070_;
  wire _071_;
  wire _072_;
  wire _073_;
  wire _074_;
  wire _075_;
  wire _076_;
  wire _077_;
  wire _078_;
  wire _079_;
  wire _080_;
  wire _081_;
  wire _082_;
  wire _083_;
  wire _084_;
  wire _085_;
  wire _086_;
  wire _087_;
  wire _088_;
  wire _089_;
  wire _090_;
  wire _091_;
  wire _092_;
  wire _093_;
  wire _094_;
  wire _095_;
  wire _096_;
  wire _097_;
  wire _098_;
  wire _099_;
  wire _100_;
  wire _101_;
  wire _102_;
  wire _103_;
  wire _104_;
  wire _105_;
  wire _106_;
  wire _107_;
  wire _108_;
  wire _109_;
  wire _110_;
  wire _111_;
  wire _112_;
  wire _113_;
  wire _114_;
  wire _115_;
  wire _116_;
  wire _117_;
  wire _118_;
  wire _119_;
  wire ERROR;
  wire NEG;
  wire ODD;
  wire ZERO;
  wire [31:0] i;
  input [3:0] i_argA;
  wire [3:0] i_argA;
  input [3:0] i_argB;
  wire [3:0] i_argB;
  input i_clk;
  wire i_clk;
  input [1:0] i_oper;
  wire [1:0] i_oper;
  input i_rsn;
  wire i_rsn;
  output [3:0] o_result;
  reg [3:0] o_result;
  output [3:0] o_status;
  reg [3:0] o_status = 4'h0;
  wire [3:0] s_result;
  assign _039_ = ~i_oper[1];
  assign _040_ = ~i_oper[0];
  assign _041_ = ~i_argA[0];
  assign _042_ = ~i_argB[0];
  assign _043_ = ~i_argB[1];
  assign _044_ = ~i_argB[2];
  assign _045_ = ~i_argB[3];
  assign _046_ = ~i_argA[2];
  assign _047_ = ~i_argA[1];
  assign _048_ = ~i_argA[3];
  assign _049_ = i_oper[1] | _040_;
  assign _050_ = _044_ & i_argA[2];
  assign _051_ = i_argB[2] | _046_;
  assign _052_ = _043_ & i_argA[1];
  assign _053_ = i_argB[1] | _047_;
  assign _054_ = _041_ & i_argB[0];
  assign _055_ = i_argA[0] | _042_;
  assign _056_ = _053_ & _054_;
  assign _057_ = _052_ | _055_;
  assign _058_ = i_argB[2] & _046_;
  assign _059_ = _044_ | i_argA[2];
  assign _060_ = i_argB[1] & _047_;
  assign _061_ = _043_ | i_argA[1];
  assign _062_ = _059_ & _061_;
  assign _063_ = _058_ | _060_;
  assign _064_ = _057_ & _062_;
  assign _065_ = _056_ | _063_;
  assign _066_ = _051_ & _065_;
  assign _067_ = _050_ | _064_;
  assign _068_ = _045_ | i_argA[3];
  assign _069_ = _041_ | _068_;
  assign _070_ = i_argB[3] | i_argA[3];
  assign _071_ = _042_ | _070_;
  assign _072_ = _069_ & _071_;
  assign _073_ = _042_ & i_argA[3];
  assign _074_ = i_argA[0] | i_argA[3];
  assign _075_ = ~_074_;
  assign _076_ = i_argB[3] & i_argA[3];
  assign _077_ = _073_ | _076_;
  assign _078_ = _075_ | _077_;
  assign _079_ = _066_ & _072_;
  assign _080_ = _067_ & _078_;
  assign _081_ = _049_ | _080_;
  assign _082_ = _079_ | _081_;
  assign _083_ = i_oper[1] & i_oper[0];
  assign _084_ = i_argB[2] | i_argB[3];
  assign _085_ = ~_084_;
  assign _086_ = i_oper[1] & _040_;
  assign _087_ = _085_ & _086_;
  assign _088_ = i_argB[0] | i_argB[1];
  assign _089_ = _087_ & _088_;
  assign _090_ = _083_ | _089_;
  assign _091_ = i_argA[0] & _090_;
  assign _092_ = _039_ & _040_;
  assign _093_ = i_oper[1] | i_oper[0];
  assign _094_ = i_argB[0] & _092_;
  assign _095_ = _091_ | _094_;
  assign _096_ = ~_095_;
  assign _097_ = _082_ & _096_;
  assign s_result[0] = ~_097_;
  assign _098_ = _047_ | _068_;
  assign _099_ = _043_ | _070_;
  assign _100_ = _098_ & _099_;
  assign _101_ = _043_ & i_argA[3];
  assign _102_ = i_argA[1] | i_argA[3];
  assign _103_ = ~_102_;
  assign _104_ = _101_ | _103_;
  assign _105_ = _076_ | _104_;
  assign _106_ = _066_ & _100_;
  assign _107_ = _067_ & _105_;
  assign _108_ = _049_ | _107_;
  assign _109_ = _106_ | _108_;
  assign _110_ = i_argA[0] & i_argA[3];
  assign _111_ = i_argA[1] ^ _110_;
  assign _112_ = _083_ & _111_;
  assign _113_ = _042_ | i_argB[1];
  assign _114_ = i_argB[1] & _092_;
  assign _115_ = i_argA[1] & _113_;
  assign _116_ = _087_ & _115_;
  assign _117_ = _112_ | _114_;
  assign _118_ = _116_ | _117_;
  assign _119_ = ~_118_;
  assign _000_ = _109_ & _119_;
  assign s_result[1] = ~_000_;
  assign _001_ = _046_ | i_argA[3];
  assign _002_ = _045_ | _001_;
  assign _003_ = _044_ | i_argB[3];
  assign _004_ = _044_ | _070_;
  assign _005_ = _002_ & _004_;
  assign _006_ = _066_ & _005_;
  assign _007_ = _048_ | _003_;
  assign _008_ = _001_ & _007_;
  assign _009_ = _067_ & _008_;
  assign _010_ = _049_ | _009_;
  assign _011_ = _006_ | _010_;
  assign _012_ = i_argB[2] & _092_;
  assign _013_ = i_argA[0] | i_argA[1];
  assign _014_ = i_argA[3] & _013_;
  assign _015_ = i_argB[0] | _043_;
  assign _016_ = i_argA[3] & _083_;
  assign _017_ = i_argA[2] ^ _014_;
  assign _018_ = _083_ & _017_;
  assign _019_ = i_argA[2] & _015_;
  assign _020_ = _087_ & _019_;
  assign _021_ = _012_ | _020_;
  assign _022_ = _018_ | _021_;
  assign _023_ = ~_022_;
  assign _024_ = _011_ & _023_;
  assign s_result[2] = ~_024_;
  assign _025_ = _073_ | _101_;
  assign _026_ = _087_ & _025_;
  assign _027_ = i_argB[3] | _093_;
  assign _028_ = _016_ | _026_;
  assign _029_ = ~_028_;
  assign _030_ = _027_ & _029_;
  assign NEG = ~_030_;
  assign _031_ = _097_ & _000_;
  assign _032_ = _024_ & _030_;
  assign ZERO = _031_ & _032_;
  assign _033_ = _084_ & _086_;
  assign _034_ = i_argA[2] | _013_;
  assign _035_ = ~_034_;
  assign _036_ = _016_ & _035_;
  assign ERROR = _033_ | _036_;
  assign _037_ = _097_ ^ _000_;
  assign _038_ = _024_ ^ _030_;
  assign ODD = _037_ ^ _038_;
  always @(posedge i_clk, negedge i_rsn)
    if (!i_rsn) o_result[0] <= 1'h0;
    else o_result[0] <= s_result[0];
  always @(posedge i_clk, negedge i_rsn)
    if (!i_rsn) o_result[1] <= 1'h0;
    else o_result[1] <= s_result[1];
  always @(posedge i_clk, negedge i_rsn)
    if (!i_rsn) o_result[2] <= 1'h0;
    else o_result[2] <= s_result[2];
  always @(posedge i_clk, negedge i_rsn)
    if (!i_rsn) o_result[3] <= 1'h0;
    else o_result[3] <= NEG;
  always @(posedge i_clk, negedge i_rsn)
    if (!i_rsn) o_status[0] <= 1'h0;
    else o_status[0] <= NEG;
  always @(posedge i_clk, negedge i_rsn)
    if (!i_rsn) o_status[1] <= 1'h0;
    else o_status[1] <= ZERO;
  always @(posedge i_clk, negedge i_rsn)
    if (!i_rsn) o_status[2] <= 1'h0;
    else o_status[2] <= ODD;
  always @(posedge i_clk, negedge i_rsn)
    if (!i_rsn) o_status[3] <= 1'h0;
    else o_status[3] <= ERROR;
  assign i = 32'd4;
  assign s_result[3] = NEG;
endmodule

src/exe_unit_w47.sv
module exe_unit_w47( i_argA, i_argB, i_oper, i_clk, i_rsn, o_result , o_status);

	parameter MBIT = 4;
	parameter NBIT = 2;

	input logic 		i_clk;
	input logic 		i_rsn;

	input logic [MBIT-1:0] i_argA;
	input logic [MBIT-1:0] i_argB;
	input logic [NBIT-1:0] i_oper;

	output logic [MBIT-1:0] o_result;
	output logic [3:0] 	o_status; 	

	
	logic [MBIT-1:0] s_result;
	logic 	ERROR;
	logic 	ODD;
	logic 	ZERO;
	logic 	NEG;

	int i;
	
	initial begin 
		o_status = '0;
		ERROR 	=	 0;
		ODD 	=	 0;
		ZERO 	=	 0;
		NEG 	=	 0;
		s_result 	= 'x;

	end

	always_comb 

	begin 
		s_result = 'x;		
		ODD = 0;	 
		ERROR = 0;

		case (i_oper)
			2'b00 :	begin 
					s_result = i_argB;			//operacja 1 odwracanie arg_A 
			      		s_result[MBIT-1] = ~i_argB[MBIT-1];
				end
			2'b01 : begin 						// operacja 2 porownanie liczb ZnMod
					if ((i_argA << 1) >= (i_argB << 1))	// A>=B po modulu
					begin
						if (i_argA[MBIT-1]==0)
						begin
							s_result = i_argA;
						end
						else if ((i_argB[MBIT-1]==0) & ((i_argA[MBIT-1])==1) | (i_argA[MBIT-1]==0))
						begin
							s_result = i_argB;
						end 
						else 
						begin
							s_result = '0;
						end
					end
					else if ((i_argA << 1) < (i_argB << 1))	// A<B po modulu
					begin 
						if ((i_argA[MBIT-1] == 0) & (i_argB[MBIT-1] == 0))
						begin
							s_result = i_argB;
						end
						else if ((i_argA[MBIT-1] == 0) & (i_argB[MBIT-1] == 1))
						begin
							s_result = i_argA; 
						end
						else 
						begin	
							s_result = '0;
						end
					end 
					else 
					begin
						s_result = '0;
					end
				end
			2'b10 : begin	
					s_result =  'x;			//operacja 3 ustawienie A_bitu
					
				if (i_argB[MBIT-1] == 1 )
				begin 			
				s_result = '0;
				ERROR = 1; 			//bland					
				end
				else if (i_argB[MBIT-1] == 0) 
				begin
					if (i_argB < MBIT)
						begin
						s_result = i_argA;
						s_result[i_argB] = 0;
						end
					else  if (i_argB >= MBIT)
						begin
						s_result = '0;
						ERROR = 1;			// balnd
						end 
					else 
						begin
						s_result = 'x;			// force else
						end
				end
				end		
			2'b11 : begin 			
						s_result = 'bx;			// operacja 4 ZnMod -> U2
					if (i_argA[MBIT-1] == 0)  
						begin		
						s_result = i_argA;
						end
					else if ((i_argA[MBIT-1] == 1) & ((i_argA << 1) == '0)) // zero minus filter
						begin
						s_result = 'bx;			// eerrorr
						ERROR = 1;			// blad
						end 
					else if (i_argA[MBIT-1] == 1)
						begin
						s_result = (i_argA - 'b1);
						s_result[MBIT-1] = ~i_argA[MBIT-1];
						s_result = ~s_result;
						end
					else 
						begin
						s_result = 'x;			// force else
						end
				end
		      default : s_result = 'x;  
		endcase

	if (s_result == '0 )
		begin 
		ZERO = 1'b1;
		end
	else if (s_result != '0)
		begin
		ZERO = 0;
		end
	else 
		begin
		ZERO = 0; 
		end	

	if (s_result[MBIT-1] == 1)
		begin
		NEG = 1'b1;
		end
	else if (s_result[MBIT-1] != 1)
		begin 
		NEG = 0;
		end
	else 
		begin 
		NEG = 0;
		end
	
	for (i = 0; i <MBIT; i = i+1 )
	begin
		if (s_result[i] == 1)
			begin
			ODD = ~ODD;	
			end
		else if (s_result[i] != 1)
			begin
			ODD = ODD;
			end
		else 
			begin 
			ODD = ODD;
			end
	end
	
	end

	always @(posedge i_clk,negedge i_rsn)
	begin 
		if (i_rsn == 0) 
		begin 
			o_status = '0;
			o_result = '0;
		end 
		else 
		begin 
			o_result <= s_result;
			o_status <= {ERROR, ODD, ZERO, NEG};
		end
	end


endmodule

src/testbench.sv
`timescale 1ns/100ps
module testbench;

parameter M_BIT = 4;
parameter N_BIT = 2;

        logic             i_clk;
        logic             i_rsn;

        logic [M_BIT-1:0] i_argA_s;	
        logic [M_BIT-1:0] i_argB_s;
        logic [N_BIT-1:0] i_oper_s;
        
	logic [M_BIT-1:0] o_result_s, o_result_ss;

exe_unit_w47 	#(.MBIT(M_BIT), .NBIT(N_BIT))	exe_model	(.i_argA(i_argA_s), .i_argB(i_argB_s), .i_oper(i_oper_s), .o_result(o_result_s)	, .i_clk, .i_rsn);		
exe_unit_w47_rtl 				exe_synth 	(.i_argA(i_argA_s), .i_argB(i_argB_s), .i_oper(i_oper_s), .o_result(o_result_ss), .i_clk, .i_rsn);	

initial
        begin
                $dumpfile("signals.vcd");
                $dumpvars(0,testbench);
		
		
		
		i_clk = 0; i_rsn = 1;               
		i_oper_s = 'b00;
		i_argA_s = '1;  i_argB_s = 'b0010;
		i_clk = 0;
		#1 
		i_clk = 1;
		#1 
		i_clk = 0;
		i_argB_s = 'b0000;
		#1
		i_clk = 1;#1	
		i_clk= 0; i_argB_s = 'b1000;
		#1
		i_clk = 1;#1
		i_clk = 0; i_argB_s = 'b1010;
		#1
		i_clk = 1;#1				// end 00
		i_clk = 0; i_argB_s = 'b1010;	i_oper_s = 01; i_argA_s ='b1100; 
		#1
		i_clk = 1;#1
		i_clk = 0; i_argA_s = 'b1000;
		#1
		i_clk = 1;#1 
		i_clk = 0; i_argB_s = 'b0010; 	i_argA_s = 'b0000;
		#1
		i_clk = 1;#1
		i_clk = 0; i_argA_s = 'b0100; 
		#1
		i_clk = 1; #1
		i_clk = 0; i_argA_s = 'b0001;	i_argB_s = 'b1010;
		#1
		i_clk = 1;#1
		i_clk = 0; i_argA_s = 'b1010; 	i_argB_s = 'b0001; 
		#1
		i_clk = 1;#1				// end 01
		i_clk = 0; i_oper_s = 'b10; i_argA_s = '1; i_argB_s = 'b1000;  		
		#1 
		i_clk = 1;#1
		i_clk = 0; i_argB_s = 'b0000;
		#1
		i_clk = 1;#1
		i_clk = 0; i_argB_s = 'b0001;
		#1
		i_clk = 1;#1
                i_clk = 0; i_argB_s = 'b0010;
		#1
		i_clk = 1;#1
                i_clk = 0; i_argB_s = 'b0011;
		#1
		i_clk = 1;#1
                i_clk = 0; i_argB_s = 'b0100;
		#1				
		i_clk = 1;#1				// end 10
                i_clk = 0; i_argA_s = 'b0010; i_oper_s = 'b11;
		#1
		i_clk = 1;#1                            
                i_clk = 0; i_argA_s = 'b0000; 
                #1
		i_clk = 1;#1                                     
                i_clk = 0; i_argA_s = 'b1000;
                #1
		i_clk = 1;#1                                     
                i_clk = 0; i_argA_s = 'b1010;
                #1
		i_clk = 1;#1                                     
                i_clk = 0;
                #1
		i_clk = 1;#1
		i_clk = 0; i_rsn = 0; 
		#1





		
	
                $finish;
        end
endmodule

src/signals.vcd
$date
	Sun Dec 10 20:34:11 2023
$end
$version
	Icarus Verilog
$end
$timescale
	100ps
$end
$scope module testbench $end
$var wire 4 ! o_result_ss [3:0] $end
$var wire 4 " o_result_s [3:0] $end
$var parameter 32 # M_BIT $end
$var parameter 32 $ N_BIT $end
$var reg 4 % i_argA_s [3:0] $end
$var reg 4 & i_argB_s [3:0] $end
$var reg 1 ' i_clk $end
$var reg 2 ( i_oper_s [1:0] $end
$var reg 1 ) i_rsn $end
$scope module exe_model $end
$var wire 4 * i_argA [3:0] $end
$var wire 4 + i_argB [3:0] $end
$var wire 1 ' i_clk $end
$var wire 2 , i_oper [1:0] $end
$var wire 1 ) i_rsn $end
$var parameter 32 - MBIT $end
$var parameter 32 . NBIT $end
$var reg 1 / ERROR $end
$var reg 1 0 NEG $end
$var reg 1 1 ODD $end
$var reg 1 2 ZERO $end
$var reg 4 3 o_result [3:0] $end
$var reg 4 4 o_status [3:0] $end
$var reg 4 5 s_result [3:0] $end
$var integer 32 6 i [31:0] $end
$upscope $end
$scope module exe_synth $end
$var wire 1 7 ERROR $end
$var wire 1 8 NEG $end
$var wire 1 9 ODD $end
$var wire 1 : ZERO $end
$var wire 1 ; _000_ $end
$var wire 1 < _001_ $end
$var wire 1 = _002_ $end
$var wire 1 > _003_ $end
$var wire 1 ? _004_ $end
$var wire 1 @ _005_ $end
$var wire 1 A _006_ $end
$var wire 1 B _007_ $end
$var wire 1 C _008_ $end
$var wire 1 D _009_ $end
$var wire 1 E _010_ $end
$var wire 1 F _011_ $end
$var wire 1 G _012_ $end
$var wire 1 H _013_ $end
$var wire 1 I _014_ $end
$var wire 1 J _015_ $end
$var wire 1 K _016_ $end
$var wire 1 L _017_ $end
$var wire 1 M _018_ $end
$var wire 1 N _019_ $end
$var wire 1 O _020_ $end
$var wire 1 P _021_ $end
$var wire 1 Q _022_ $end
$var wire 1 R _023_ $end
$var wire 1 S _024_ $end
$var wire 1 T _025_ $end
$var wire 1 U _026_ $end
$var wire 1 V _027_ $end
$var wire 1 W _028_ $end
$var wire 1 X _029_ $end
$var wire 1 Y _030_ $end
$var wire 1 Z _031_ $end
$var wire 1 [ _032_ $end
$var wire 1 \ _033_ $end
$var wire 1 ] _034_ $end
$var wire 1 ^ _035_ $end
$var wire 1 _ _036_ $end
$var wire 1 ` _037_ $end
$var wire 1 a _038_ $end
$var wire 1 b _039_ $end
$var wire 1 c _040_ $end
$var wire 1 d _041_ $end
$var wire 1 e _042_ $end
$var wire 1 f _043_ $end
$var wire 1 g _044_ $end
$var wire 1 h _045_ $end
$var wire 1 i _046_ $end
$var wire 1 j _047_ $end
$var wire 1 k _048_ $end
$var wire 1 l _049_ $end
$var wire 1 m _050_ $end
$var wire 1 n _051_ $end
$var wire 1 o _052_ $end
$var wire 1 p _053_ $end
$var wire 1 q _054_ $end
$var wire 1 r _055_ $end
$var wire 1 s _056_ $end
$var wire 1 t _057_ $end
$var wire 1 u _058_ $end
$var wire 1 v _059_ $end
$var wire 1 w _060_ $end
$var wire 1 x _061_ $end
$var wire 1 y _062_ $end
$var wire 1 z _063_ $end
$var wire 1 { _064_ $end
$var wire 1 | _065_ $end
$var wire 1 } _066_ $end
$var wire 1 ~ _067_ $end
$var wire 1 !" _068_ $end
$var wire 1 "" _069_ $end
$var wire 1 #" _070_ $end
$var wire 1 $" _071_ $end
$var wire 1 %" _072_ $end
$var wire 1 &" _073_ $end
$var wire 1 '" _074_ $end
$var wire 1 (" _075_ $end
$var wire 1 )" _076_ $end
$var wire 1 *" _077_ $end
$var wire 1 +" _078_ $end
$var wire 1 ," _079_ $end
$var wire 1 -" _080_ $end
$var wire 1 ." _081_ $end
$var wire 1 /" _082_ $end
$var wire 1 0" _083_ $end
$var wire 1 1" _084_ $end
$var wire 1 2" _085_ $end
$var wire 1 3" _086_ $end
$var wire 1 4" _087_ $end
$var wire 1 5" _088_ $end
$var wire 1 6" _089_ $end
$var wire 1 7" _090_ $end
$var wire 1 8" _091_ $end
$var wire 1 9" _092_ $end
$var wire 1 :" _093_ $end
$var wire 1 ;" _094_ $end
$var wire 1 <" _095_ $end
$var wire 1 =" _096_ $end
$var wire 1 >" _097_ $end
$var wire 1 ?" _098_ $end
$var wire 1 @" _099_ $end
$var wire 1 A" _100_ $end
$var wire 1 B" _101_ $end
$var wire 1 C" _102_ $end
$var wire 1 D" _103_ $end
$var wire 1 E" _104_ $end
$var wire 1 F" _105_ $end
$var wire 1 G" _106_ $end
$var wire 1 H" _107_ $end
$var wire 1 I" _108_ $end
$var wire 1 J" _109_ $end
$var wire 1 K" _110_ $end
$var wire 1 L" _111_ $end
$var wire 1 M" _112_ $end
$var wire 1 N" _113_ $end
$var wire 1 O" _114_ $end
$var wire 1 P" _115_ $end
$var wire 1 Q" _116_ $end
$var wire 1 R" _117_ $end
$var wire 1 S" _118_ $end
$var wire 1 T" _119_ $end
$var wire 32 U" i [31:0] $end
$var wire 4 V" i_argA [3:0] $end
$var wire 4 W" i_argB [3:0] $end
$var wire 1 ' i_clk $end
$var wire 2 X" i_oper [1:0] $end
$var wire 1 ) i_rsn $end
$var wire 4 Y" s_result [3:0] $end
$var reg 4 Z" o_result [3:0] $end
$var reg 4 [" o_status [3:0] $end
$upscope $end
$upscope $end
$enddefinitions $end
$comment Show the parameter values. $end
$dumpall
b10 .
b100 -
b10 $
b100 #
$end
#0
$dumpvars
b0 ["
bx Z"
b1010 Y"
b0 X"
b10 W"
b1111 V"
b100 U"
0T"
1S"
1R"
0Q"
1P"
1O"
1N"
0M"
0L"
1K"
1J"
1I"
0H"
0G"
0F"
0E"
0D"
1C"
0B"
1A"
1@"
1?"
1>"
1="
0<"
0;"
0:"
19"
08"
07"
06"
15"
04"
03"
12"
01"
00"
1/"
1."
1-"
0,"
1+"
1*"
0)"
0("
1'"
1&"
1%"
1$"
1#"
1""
1!"
1~
0}
0|
1{
0z
1y
1x
0w
1v
0u
1t
0s
1r
0q
1p
0o
0n
1m
1l
0k
0j
0i
1h
1g
0f
1e
0d
1c
1b
1a
1`
0_
0^
1]
0\
0[
0Z
0Y
1X
0W
0V
0U
1T
1S
1R
0Q
0P
0O
0N
0M
0L
0K
0J
1I
1H
0G
1F
1E
1D
1C
1B
0A
1@
1?
1>
1=
1<
0;
0:
09
18
07
b100 6
b1010 5
b0 4
bx 3
02
01
10
0/
b0 ,
b10 +
b1111 *
1)
b0 (
0'
b10 &
b1111 %
bx "
bx !
$end
#10
b1 4
b1010 "
b1010 3
b1010 !
b1010 Z"
b1 ["
1'
#20
19
b1000 Y"
1Z
0`
1H"
1;
1F"
1T"
1E"
1N
0S"
1o
1B"
1J
0R"
1f
0p
05"
0O"
11
b100 6
b1000 5
b0 &
b0 +
b0 W"
0'
#30
b101 ["
b1000 !
b1000 Z"
b101 4
b1000 "
b1000 3
1'
#40
1:
09
b0 Y"
08
1[
0a
02"
1Y
0h
1)"
11"
1V
b100 6
00
12
01
b0 5
b1000 &
b1000 +
b1000 W"
0'
#50
b10 4
b0 "
b0 3
b0 !
b0 Z"
b10 ["
1'
#60
0:
19
b10 Y"
0Z
1`
0;
0T"
0E"
0N
1S"
0o
0B"
0J
1R"
0f
1p
15"
1O"
11
b100 6
02
b10 5
b1010 &
b1010 +
b1010 W"
0'
#70
b100 ["
b10 !
b10 Z"
b100 4
b10 "
b10 3
1'
#80
1:
09
b0 Y"
1Z
0`
1;
1T"
0S"
1|
0R"
1z
0{
1L
0O"
1w
0y
0I
0l
09"
1d
1j
0x
0K"
0L"
0P"
0H
0c
1:"
b100 6
12
01
b0 5
b1100 %
b1100 *
b1100 V"
b1 (
b1 ,
b1 X"
0'
#90
b10 4
b0 "
b0 3
b0 !
b0 Z"
b10 ["
1'
#100
1,"
1G"
1A
0."
0I"
0E
1}
0-"
0H"
0D
1n
0~
1^
1i
0m
0L
0]
b100 6
b0 5
b1000 %
b1000 *
b1000 V"
0'
#110
1'
#120
0:
19
b10 Y"
0Z
1`
0;
0J"
0G"
1E"
0A"
0T
1("
1D"
0@"
0*"
1F"
12"
1k
0&"
0'"
0C"
1h
0#"
0)"
01"
11
b100 6
02
b10 5
b0 %
b0 *
b0 V"
b10 &
b10 +
b10 W"
0'
#130
b100 4
b10 "
b10 3
b10 !
b10 Z"
b100 ["
1'
#140
0[
1a
0:
19
0S
b100 Y"
1Z
0`
0F
1;
1J"
0,"
0A
1."
1I"
0E
0}
0C
1-"
1H"
0D
0n
0<
1~
0^
0i
1m
1L
1]
b100 6
11
b100 5
b100 %
b100 *
b100 V"
0'
#150
b100 !
b100 Z"
b100 "
b100 3
1'
#160
0Z
1`
0:
19
0>"
b1 Y"
1[
0a
0/"
1S
1F
0%"
0,"
1G"
1A
0."
0I"
0""
1A"
1}
1C
0-"
0H"
0+"
0!"
1@"
02"
1n
1<
0~
0("
0^
0h
1#"
11"
0d
1i
0m
1'"
1H
0L
1]
b100 6
11
b1 5
b1010 &
b1010 +
b1010 W"
b1 %
b1 *
b1 V"
0'
#170
b1 "
b1 3
b1 !
b1 Z"
1'
#180
0:
19
b1 Y"
0Z
1`
1I"
1E
0>"
0G"
0A
1H"
1D
0/"
0}
1~
0,"
0|
1{
1%"
0+"
0r
0N"
1o
1B"
0z
12"
1y
1""
0*"
1T
0D"
1L
0e
1f
1h
0p
1q
0w
01"
1J
1d
0j
0k
1x
1!"
0&"
1C"
1L"
0P"
1I
b100 6
11
b1 5
b1 &
b1 +
b1 W"
b1010 %
b1010 *
b1010 V"
0'
#190
1'
#200
1:
09
b0 Y"
1Z
0`
1-"
1>"
1P"
1+"
17
1/"
1&"
1N"
1*"
02"
1\
0n
0L"
13"
1."
1e
0h
0q
1)"
11"
05"
0d
0i
1m
1r
1K"
0L
1N
0b
1c
1l
b100 6
12
1/
01
b0 5
b1000 &
b1000 +
b1000 W"
b1111 %
b1111 *
b1111 V"
b10 (
b10 ,
b10 X"
0'
#210
b1010 4
b0 "
b0 3
b0 !
b0 Z"
b1010 ["
1'
#220
19
0:
0Z
1`
0S
b1110 Y"
18
0[
0a
0;
0R
0Y
0T"
1Q
0X
1S"
1P
1W
1Q"
1O
1U
14"
07
12"
0\
1h
0)"
01"
11
b100 6
10
02
0/
b1110 5
b0 &
b0 +
b0 W"
0'
#230
b101 ["
b1110 !
b1110 Z"
b101 4
b1110 "
b1110 3
1'
#240
b1101 Y"
1;
0>"
1T"
0="
0-"
0S"
1<"
0+"
0Q"
18"
0*"
0P"
17"
0&"
0N"
16"
0e
15"
b100 6
11
b1101 5
b1 &
b1 +
b1 W"
0'
#250
b1101 "
b1101 3
b1101 !
b1101 Z"
1'
#260
1a
1S
19
1R
b1011 Y"
0`
0Q
0;
1-"
0H"
0P
0T"
1+"
0F"
0O
1S"
1*"
0E"
0N
1Q"
1&"
0o
0B"
0J
1P"
1e
0f
1p
1N"
b100 6
11
b1011 5
b10 &
b10 +
b10 W"
0'
#270
b1011 !
b1011 Z"
b1011 "
b1011 3
1'
#280
08
b111 Y"
1Y
0S
1X
0R
0-"
0W
1Q
0+"
0U
1P
0*"
0T
1O
0&"
1N
0e
1J
b100 6
00
11
b111 5
b11 &
b11 +
b11 W"
0'
#290
b100 4
b111 "
b111 3
b111 !
b111 Z"
b100 ["
1'
#300
09
1:
1Z
1[
0a
1>"
b0 Y"
0`
1S
1="
1;
1R
1-"
1H"
0D
0<"
1T"
0Q
1+"
1F"
0C
08"
0S"
0P
1*"
1E"
1T
0B
04"
17
07"
0Q"
0O
1&"
1o
1B"
0m
0>
02"
1\
06"
1P"
1N
1e
1f
0g
1n
0p
11"
05"
1N"
1J
b100 6
12
1/
01
b0 5
b100 &
b100 +
b100 W"
0'
#310
b1010 ["
b0 !
b0 Z"
b1010 4
b0 "
b0 3
1'
#320
0Z
1`
0:
19
0;
1,"
1G"
b10 Y"
1[
0a
0T"
1}
0-"
1S
07
1S"
1|
0~
0H"
1R
0\
1R"
1z
1C
0{
0@
0F"
0Q
03"
17"
1M"
1u
1B
0y
0?
0*"
1("
0E"
0T
1L"
0M
0c
10"
1d
1i
1k
0v
0#"
0&"
0'"
0B"
0K"
1<
0I
0L
0N
11
b100 6
02
0/
b10 5
b11 (
b11 ,
b11 X"
b10 %
b10 *
b10 V"
0'
#330
b100 4
b10 "
b10 3
b10 !
b10 Z"
b100 ["
1'
#340
1:
09
b0 Y"
1Z
0`
1;
1T"
1F"
0S"
1E"
0R"
1^
1p
1D"
0M"
0]
1j
0o
0C"
0L"
0P"
0H
b100 6
12
01
b0 5
b0 %
b0 *
b0 V"
0'
#350
b10 ["
b0 !
b0 Z"
b10 4
b0 "
b0 3
1'
#360
0:
19
b1000 Y"
18
0[
1a
1A
0Y
0C
1@
0X
17
0B
1?
1*"
0("
1T
0D"
1W
1_
0k
1#"
1&"
1'"
1B"
1C"
1K
b100 6
02
1/
bx 5
b1000 %
b1000 *
b1000 V"
0'
#370
b1000 4
bx "
bx 3
b1000 !
b1000 Z"
b1101 ["
1'
#380
0a
b1110 Y"
0Z
1`
0S
0;
0R
0T"
1Q
07
1S"
1M
0_
1R"
1L
0^
0p
1M"
1I
1]
0j
1o
1L"
1P"
1H
11
b100 6
10
b1110 5
0/
b1010 %
b1010 *
b1010 V"
0'
#390
b101 ["
b1110 !
b1110 Z"
b101 4
b1110 "
b1110 3
1'
#400
0'
#410
1'
#420
b0 ["
b0 !
b0 Z"
b0 "
b0 3
b0 4
0)
0'
